cryptoadvance/specterext/liquidissuer/__init__.py
cryptoadvance/specterext/liquidissuer/__main__.py
cryptoadvance/specterext/liquidissuer/amp.py
cryptoadvance/specterext/liquidissuer/app_config.py
cryptoadvance/specterext/liquidissuer/config.py
cryptoadvance/specterext/liquidissuer/controller.py
cryptoadvance/specterext/liquidissuer/rpc.py
cryptoadvance/specterext/liquidissuer/service.py
cryptoadvance/specterext/liquidissuer/static/liquidissuer/custom_select.css
cryptoadvance/specterext/liquidissuer/static/liquidissuer/custom_select.js
cryptoadvance/specterext/liquidissuer/static/liquidissuer/helpers.js
cryptoadvance/specterext/liquidissuer/static/liquidissuer/styles.css
cryptoadvance/specterext/liquidissuer/static/liquidissuer/css/styles.css
cryptoadvance/specterext/liquidissuer/static/liquidissuer/img/add.svg
cryptoadvance/specterext/liquidissuer/static/liquidissuer/img/asset.svg
cryptoadvance/specterext/liquidissuer/static/liquidissuer/img/blockstream_logo.png
cryptoadvance/specterext/liquidissuer/static/liquidissuer/img/category.svg
cryptoadvance/specterext/liquidissuer/static/liquidissuer/img/check.svg
cryptoadvance/specterext/liquidissuer/static/liquidissuer/img/check_green.svg
cryptoadvance/specterext/liquidissuer/static/liquidissuer/img/company.svg
cryptoadvance/specterext/liquidissuer/static/liquidissuer/img/delete.svg
cryptoadvance/specterext/liquidissuer/static/liquidissuer/img/diamond-multiple.svg
cryptoadvance/specterext/liquidissuer/static/liquidissuer/img/lock.svg
cryptoadvance/specterext/liquidissuer/static/liquidissuer/img/managers.svg
cryptoadvance/specterext/liquidissuer/static/liquidissuer/img/pending_orange.svg
cryptoadvance/specterext/liquidissuer/static/liquidissuer/img/person.svg
cryptoadvance/specterext/liquidissuer/static/liquidissuer/img/settings.svg
cryptoadvance/specterext/liquidissuer/static/liquidissuer/img/treasury.svg
cryptoadvance/specterext/liquidissuer/static/liquidissuer/img/unlock.svg
cryptoadvance_liquidissuer-0.2.4.dist-info/LICENSE
cryptoadvance_liquidissuer-0.2.4.dist-info/METADATA
cryptoadvance_liquidissuer-0.2.4.dist-info/WHEEL
cryptoadvance_liquidissuer-0.2.4.dist-info/top_level.txt
cryptoadvance_liquidissuer-0.2.4.dist-info/RECORD
