Metadata-Version: 2.1
Name: cryptoadvance-liquidissuer
Version: 0.2.4
Summary: A UI for Issuing Liquid and Amp tokens
Home-page: https://github.com/cryptoadvance/specterext-liquidissuer
Author: Stepan Snigirev
Author-email: stepan@specter.solutions
Project-URL: Bug Tracker, https://github.com/cryptoadvance/specterext-liquidissuer/issues
Classifier: Programming Language :: Python :: 3
Classifier: License :: OSI Approved :: MIT License
Classifier: Operating System :: OS Independent
Requires-Python: >=3.6
License-File: LICENSE
